steambot/__init__.py
steambot/__main__.py
steambot/bot.py
steambot/config.py
steambot/feeds.py
steambot/index.py
steambot/logconfig.py
steambot/scripts.py
steambot/state.py
steambot-1.2.6.dist-info/METADATA
steambot-1.2.6.dist-info/WHEEL
steambot-1.2.6.dist-info/entry_points.txt
steambot-1.2.6.dist-info/licenses/LICENSE
steambot-1.2.6.dist-info/RECORD
