Metadata-Version: 2.1
Name: steambot
Version: 1.2.6
Summary: A Discord bot for Steam news feeds.
Project-URL: Source code, https://github.com/Faxmachinen/steamnews
License-File: LICENSE
Keywords: Discord,RSS,Steam,bot,news
Requires-Python: >=3.9
Requires-Dist: beautifulsoup4~=4.11
Requires-Dist: py-cord~=2.2
Requires-Dist: python-dateutil~=2.8
Requires-Dist: requests~=2.28
Requires-Dist: whoosh~=2.7
